[
  {
    "title": "Backend Engineer / Java Developer",
    "company": "Migros One",
    "location": "Istanbul, Türkiye",
    "description": "Who are we? Our business is technology, food and retail. We are a young team that combines all resources with technology; Our goal is to provide an excellent e-commerce service to meet your needs. In short, you can call us Migros One. 😉 Today, as a team that holds the “Great Place To Work” certificate with the contributions of our employees we produce, learn and develop together. We rediscover our passion for our business every day and build Migros One culture together. Our Culture We are #ONE to create a better tomorrow for our community. Our way of working includes four core values that we strive to act: 1. Take accountability with passion 2. Drive innovation with curiosity 3. Make a difference for our customers 4. Create open communication We live these values every day and create an environment where everyone enjoys working. Our business culture based on trust, openness and innovation has been recognized with our “Great Place To Work” certificate! What Do We Do? As Migros One; We spread happiness in being the pioneer of innovation in the field of food and retail technology with our brands Migros Sanal Market, Migros Hemen, Migros Extra, Migros Yemek, Macroonline, Tazedirekt, Mion and Petimo! Our determination to find fast and effective solutions always keeps us one step ahead. Our team's passion and energy make their jobs enjoyable. Thanks to our people-oriented approach, we aim to create a more comfortable and practical world for everyone by using them all. We constantly strive to provide the best experience to our consumers and employees!As Migros One team, we get excited with every member of our team creating his/her own career story! If you would like to be a part of this visionary and tech-savvy e-commerce team, don’t wait! Make your application! We are looking for Backend Engineer who will be on our team. What You'll Be Doing: Contributing the software development lifecycle. (technical design, implementation, testing, deployment, and monitoring.), Identification ability of engineering bottlenecks and discussing potential solutions. (redact RFC and ADR documents.), Responsible for the quality assurance of the work we work on, Applying a product mindset to back-end systems, Regularly presenting new ideas and techniques in Brown Bag Sessions, Improving the System Design of the solution architecture on production. What You'll Bring: Minimum 4 years of experience as a back-end engineer, Production experience with Java 21 (11 or 17 is also fine), REST Conventions, Redis and Docker, Hands-on implementation practice of Object-Oriented Design Patterns is a must, Familiarity of security concepts and methodologies is a nice-to-have. (OAuth2, OIDC, Authorization Code Flow, etc.), Knowledge of Messaging Solutions (RabbitMQ, Apache Kafka, or similar) is required, Experience with AWS, GCP, OpenShift, Azure or similar is highly desired, Experience with Clean or Hexagonal Architecture is a nice-to-have, Domain-Driven Design is a nice-to-have. (Tactical DDD, Aggregate Design Rules, Eventual and Strong Consistency, etc.), Knowledge of Microservices Patterns is a nice-to-have. (Transactional Outbox, Data Consistency with Saga.), Unit, Integration and E2E test knowledge is a plus.",
    "link": "https://tr.linkedin.com/jobs/view/backend-engineer-java-developer-at-migros-one-4296713421",
    "found_at": "2026-05-05 04:59:48"
  },
  {
    "title": "Backend Engineer (Node.js)",
    "company": "Cozmopol",
    "location": "Sisli, Istanbul, Türkiye",
    "description": "Cozmopol Hakkında Cozmopol, kullanıcıların avatarlar ile etkileşime girebildiği, yapay zeka destekli 3D bir alışveriş deneyimi sunan bir platformdur. Hedefimiz yüksek performanslı ve ölçeklenebilir bir altyapı ile global bir ürün ortaya çıkarmak. Pozisyon Hakkında Backend sistemlerinin geliştirilmesi ve ölçeklenmesinde aktif rol alacak bir Node.js Backend Developer arıyoruz. Bu pozisyonda, API geliştirme, sistem mimarisi ve performans konularında sorumluluk alacaksın. Sorumluluklar Node.js ile RESTful API geliştirme Mikroservis mimarisi kurma ve geliştirme Performans ve ölçeklenebilirlik iyileştirmeleri yapma Authentication ve authorization süreçlerini yönetme Gerçek zamanlı sistemler geliştirme (WebSocket vb.) Üçüncü parti servis entegrasyonları Frontend ve diğer ekiplerle koordineli çalışma Temiz ve sürdürülebilir kod yazımı Aranan Nitelikler Node.js (Express veya Fastify) deneyimi REST API ve sistem tasarımı bilgisi Veritabanı deneyimi (MongoDB, PostgreSQL vb.) Redis, cache ve queue sistemleri hakkında bilgi Docker ve temel DevOps süreçlerine aşinalık Git kullanımı Tercih Sebepleri Cloud (AWS, GCP, Azure) deneyimi Gerçek zamanlı sistem tecrübesi Yüksek trafikli sistemlerde çalışma deneyimi",
    "link": "https://tr.linkedin.com/jobs/view/backend-engineer-node-js-at-cozmopol-4408971661",
    "found_at": "2026-05-05 04:59:48"
  },
  {
    "title": "Backend-Frontend Developer",
    "company": "genessencedx",
    "location": "Türkiye",
    "description": "Yapılacak olan TÜSEB başvurumuz için ekip arkadaşları arıyoruz. Proje kapsamında NGS datasının işlenmesi ve varyant analizi (tespit, anotasyon, filtreleme ve görselleştirme) süreçlerini uçtan uca destekleyen bir biyoinformatik altyapı olacaktır. Backend Geliştirici: API geliştirme konusunda deneyimli Veritabanı yönetimi ve tasarımı bilgisine sahip Python veya Node.js teknolojilerinde tecrübeli Bilgisayar Mühendisliği veya Yazılım Mühendisliği bölümünden mezun (TÜSEB Başvurusunda diploma sunma zorunluluğu bulunmaktadır bu nedenle sadece bilgisayar mühendisliği veya yazılım mühendisliği bölümünden mezun kişiler ile görüşme yapılacaktır) En az 2 yıl iş tecrübesi olan Frontend Geliştirici: React, Vue.js framework’lerinde deneyimli Veri görselleştirme konusunda bilgi sahibi API entegrasyonu süreçlerine hakim Bilgisayar Mühendisliği veya Yazılım Mühendisliği bölümünden mezun (TÜSEB Başvurusunda diploma sunma zorunluluğu bulunmaktadır bu nedenle sadece bilgisayar mühendisliği veya yazılım mühendisliği bölümünden mezun kişiler ile görüşme yapılacaktır) En az 2 yıl iş tecrübesi olan Önemli Not Bu ilan, Türkiye Sağlık Enstitüleri Başkanlığı (TÜSEB) proje başvurusu kapsamında ön başvuru toplamak amacıyla paylaşılmaktadır. Projenin desteklenmesi halinde işe alım gerçekleştirilecektir. Başvuru Süreci Başvurularınızı, özgeçmişiniz ile birlikte info@genessencedx.com adresine iletebilirsiniz. Uygun adaylarla proje süreci içerisinde iletişime geçilecektir. Son Başvuru Tarihi: 10.05.2026",
    "link": "https://tr.linkedin.com/jobs/view/backend-frontend-developer-at-genessencedx-4408168120",
    "found_at": "2026-05-05 08:00:23"
  },
  {
    "title": "Senior Fullstack Developer (React / Node.js)",
    "company": "Nuevo Softwarehouse",
    "location": "Türkiye",
    "description": "Nuevo Softwarehouse olarak, Almany a merkezli üretim şirketi süreçlerinde değerlendirilmek üzere Senior Fullstack Developer (React / Node.js ) ekip arkadaşı arayışımız bulunmaktadır. Çalışma Dili: İngilizce Çalışma Şekli: Remote Responsibilities Developing and maintaining a modern React frontend (min 5 years) Integrating Backend APIs (REST) Integrating cloud services, particularly for file storage and databases Setting up and improving CI/CD pipelines Establishing build, deployment, and containerization (Docker) processes Ensuring code quality, performance, and maintainability Required Qualifications Experience in developing web applications with Node.js for production environments (min. 5 years) Experience in JavaScript development (min. 5 years) Experience in React development (min. 5 years) Experience with REST APIs and frontend integration (min. 3 years) German: Intermediate level (B1) English: Upper-Intermediate / Independent user level (B2) Preferred Qualifications (Nice to Have) Basic knowledge of relational databases (e.g., SQL) Knowledge of Docker and containerization Basic knowledge of authentication concepts (e.g., Entra ID) Basic understanding of Kubernetes Experience with Blob Storage (file upload/management) Experience with CI/CD pipelines (e.g., Azure DevOps)",
    "link": "https://tr.linkedin.com/jobs/view/senior-fullstack-developer-react-node-js-at-nuevo-softwarehouse-4408172212",
    "found_at": "2026-05-05 08:00:23"
  },
  {
    "title": "Mobile Developer - React Native",
    "company": "Jobgether",
    "location": "Greater Istanbul",
    "description": "This position is posted by Jobgether on behalf of a partner company. We are currently looking for a Mobile Developer - React Native in Turkey. You will join a fast-moving, globally distributed engineering team focused on building high-performance mobile applications for a cutting-edge digital trading platform. The role involves designing and delivering new mobile features that enhance user experience in real-time financial environments. You will work on highly scalable systems that support rapid user growth while maintaining speed and reliability. A strong emphasis is placed on crafting seamless data visualization experiences powered by large-scale data streams. Operating in an agile and collaborative setting, you will contribute to both technical design and product evolution. This position offers the opportunity to shape impactful mobile solutions used by a global user base in a dynamic fintech space. You will collaborate closely with engineers, designers, and product teams to continuously improve the mobile experience. Accountabilities Develop and enhance mobile applications using React Native, focusing on performance, usability, and scalability Build and ship new features using agile methodologies in a fast-paced development environment Optimize application responsiveness and ensure smooth real-time user experiences at scale Implement and improve data visualization components based on large and complex datasets Integrate RESTful APIs and WebSocket-based services for real-time functionality Collaborate with cross-functional teams to define, design, and deliver innovative mobile solutions Contribute to code quality, testing, and continuous improvement of mobile architecture Requirements Strong proficiency in JavaScript (ES6+) and solid experience with React Native Hands-on experience with Redux and modern mobile development workflows Good understanding of Expo and React Native ecosystem best practices Experience working with REST APIs and WebSockets for real-time applications Familiarity with mobile performance optimization and scalable app architecture Knowledge of native mobile development (Swift and/or Kotlin) is a plus Experience with Xcode and Android Studio is advantageous Strong problem-solving skills and ability to work in an agile, distributed team environment Passion for building high-quality, user-centric mobile applications Benefits Fully remote work with global flexibility Competitive compensation package Strong focus on career development and continuous learning Mentorship from experienced engineers and industry professionals Collaborative and supportive international team culture Regular knowledge-sharing initiatives and technical workshops Team-building activities and social engagement opportunities (remote and in-person) How Jobgether Works We use an AI-powered matching process to ensure your application is reviewed quickly, objectively, and fairly against the role's core requirements. Our system identifies the top-fitting candidates, and this shortlist is then shared directly with the hiring company. The final decision and next steps (interviews, assessments) are managed by their internal team. We appreciate your interest and wish you the best! Why Apply Through Jobgether? Data Privacy Notice: By submitting your application, you acknowledge that Jobgether will process your personal data to evaluate your candidacy and share relevant information with the hiring employer. This processing is based on legitimate interest and pre-contractual measures under applicable data protection laws (including GDPR). You may exercise your rights (access, rectification, erasure, objection) at any time. We may use artificial intelligence (AI) tools to support parts of the hiring process, such as reviewing applications, analyzing resumes, or assessing responses. These tools assist our recruitment team but do not replace human judgment. Final hiring decisions are ultimately made by humans. If you would like more information about how your data is processed, please contact us.",
    "link": "https://tr.linkedin.com/jobs/view/mobile-developer-react-native-at-jobgether-4408979824",
    "found_at": "2026-05-05 08:00:23"
  },
  {
    "title": "Senior Front-End Developer (Vue.js / React)",
    "company": "Webimonline Bilgi Teknolojileri",
    "location": "Ankara, Ankara, Türkiye",
    "description": "Senior Front-End Developer (Vue.js / React) Ankara'daki ofisimizde çalışmak üzere, modern arayüzler geliştirmeyi seven ve kullanıcı deneyimini önceliklendiren Senior Front-End Developer arıyoruz. Aradığımız Profil İleri seviye Vue.js bilgisi React.js konusunda deneyimli Figma’yı aktif ve profesyonel kullanabilen UI/UX hassasiyeti yüksek, tasarımı birebir koda dökebilen Responsive ve pixel-perfect geliştirme konusunda deneyimli RESTful API entegrasyonlarına hakim Modern JavaScript (ES6+) konusunda güçlü Component bazlı mimari konusunda deneyimli Git kullanımına hakim Gerektiğinde tasarımları framework bağımsız şekilde, temiz ve optimize edilmiş HTML/CSS olarak geliştirebilen 🧩 Tercihen Figma üzerinde tasarım oluşturabilen veya tasarım olmadan da kullanıcı dostu arayüzler tasarlayıp geliştirebilen Nuxt.js ve/veya Next.js deneyimi Tailwind / SCSS bilgisi Performans optimizasyonu ve SEO bilgisi Agile / Scrum süreçlerine aşinalık 💼 Sorumluluklar Figma tasarımlarını yüksek doğrulukla koda dökmek Vue.js ve React projelerinde aktif geliştirme yapmak Mevcut projelerde UI geliştirme ve iyileştirme yapmak API entegrasyonlarını gerçekleştirmek Performans ve kullanıcı deneyimini sürekli optimize etmek İlgilenen adayların güncel CV ve portföylerini ik@webimonline.com adresine iletmeleri rica olunur.",
    "link": "https://tr.linkedin.com/jobs/view/senior-front-end-developer-vue-js-react-at-webimonline-bilgi-teknolojileri-4408146946",
    "found_at": "2026-05-05 08:00:23"
  }
]